qy/__init__.py
qy/queue.py
qy/settings.py
qy/migrations/20211106190347182_jobs.yaml
qy-0.3.6.dist-info/LICENSE
qy-0.3.6.dist-info/METADATA
qy-0.3.6.dist-info/WHEEL
qy-0.3.6.dist-info/top_level.txt
qy-0.3.6.dist-info/RECORD
