Metadata-Version: 2.1
Name: qy
Version: 0.3.6
Summary: An asyncpg-based queue library for python
Home-page: https://gitlab.com/blackearth/qy
Author: Sean Harrison
Author-email: sah@bookgenesis.com
License: MPL 2.0
Platform: UNKNOWN
Classifier: Development Status :: 3 - Alpha
Classifier: Intended Audience :: Developers
Classifier: License :: OSI Approved :: Mozilla Public License 2.0 (MPL 2.0)
Classifier: Programming Language :: Python :: 3
License-File: LICENSE
Provides-Extra: dev
Provides-Extra: test
